mintchoco/__init__.py
mintchoco/base_types.py
mintchoco/client.py
mintchoco/http.py
mintchoco/py.typed
mintchoco/types.py
mintchoco/model/__init__.py
mintchoco/model/base.py
mintchoco/model/image.py
mintchoco/model/info.py
mintchoco/model/list.py
mintchoco/model/search.py
mintchoco-6.0.0.dist-info/LICENSE
mintchoco-6.0.0.dist-info/METADATA
mintchoco-6.0.0.dist-info/WHEEL
mintchoco-6.0.0.dist-info/top_level.txt
mintchoco-6.0.0.dist-info/RECORD
